setup.py
botbits/__init__.py
botbits/bot.py
botbits/commands.py
botbits/handlers.py
botbits/tumblr.py
botbits/twitter.py
botbits.egg-info/PKG-INFO
botbits.egg-info/SOURCES.txt
botbits.egg-info/dependency_links.txt
botbits.egg-info/requires.txt
botbits.egg-info/top_level.txt
botbits/conf/__init__.py
botbits/conf/default_settings.py