Metadata-Version: 1.0
Name: botbits
Version: 0.0.1
Summary: Bits for building bots.
Home-page: https://github.com/awentzonline/botbits
Author: Adam Wentz, Chris Sinchok
Author-email: awentz@theonion.com
License: MIT
Platform: UNKNOWN
